setup.py
google/__init__.py
google/api/__init__.py
google/api/annotations_pb2.py
google/api/http_pb2.py
google/datastore/__init__.py
google/datastore/v1beta3/__init__.py
google/datastore/v1beta3/datastore_pb2.py
google/datastore/v1beta3/entity_pb2.py
google/datastore/v1beta3/query_pb2.py
google/protobuf/__init__.py
google/protobuf/any_pb2.py
google/protobuf/descriptor_pb2.py
google/protobuf/struct_pb2.py
google/protobuf/timestamp_pb2.py
google/protobuf/wrappers_pb2.py
google/rpc/__init__.py
google/rpc/code_pb2.py
google/rpc/status_pb2.py
google/type/__init__.py
google/type/latlng_pb2.py
proto_google_datastore_v1beta3.egg-info/PKG-INFO
proto_google_datastore_v1beta3.egg-info/SOURCES.txt
proto_google_datastore_v1beta3.egg-info/dependency_links.txt
proto_google_datastore_v1beta3.egg-info/requires.txt
proto_google_datastore_v1beta3.egg-info/top_level.txt