Metadata-Version: 1.1
Name: proto-google-datastore-v1beta3
Version: 1.0.0-beta.2
Summary: Generated files from protocol buffers for Cloud Datastore v1beta3.
Home-page: https://github.com/GoogleCloudPlatform/google-cloud-datastore
Author: Google Inc
Author-email: gcd-discuss@google.com
License: Apache
Platform: UNKNOWN
Classifier: Development Status :: 4 - Beta
Classifier: Intended Audience :: Developers
Classifier: Programming Language :: Python :: 2.7
